djangostreetmap/__init__.py
djangostreetmap/admin.py
djangostreetmap/annotations.py
djangostreetmap/apps.py
djangostreetmap/functions.py
djangostreetmap/json_object.py
djangostreetmap/layers.py
djangostreetmap/management/commands/import_land.py
djangostreetmap/maplibre/__init__.py
djangostreetmap/migrations/0001_initial.py
djangostreetmap/migrations/0002_osmhighway.py
djangostreetmap/migrations/0003_auto_20210906_0359.py
djangostreetmap/migrations/0004_osmislands.py
djangostreetmap/migrations/0005_osmislandsareas.py
djangostreetmap/migrations/0006_auto_20211025_2148.py
djangostreetmap/migrations/0007_simplifiedlandpolygon_delete_osmadminboundary_and_more.py
djangostreetmap/migrations/__init__.py
djangostreetmap/models.py
djangostreetmap/osm_update.py
djangostreetmap/templates/leaflet_tile_layers.html
djangostreetmap/tests.py
djangostreetmap/tilegenerator.py
djangostreetmap/timer.py
djangostreetmap/urls.py
djangostreetmap/views.py
djangostreetmap/wsgi.py
maplibre/README.md
maplibre/__init__.py
maplibre/basemodel.py
maplibre/color.py
maplibre/layer.py
maplibre/light.py
maplibre/osm_liberty.json
maplibre/osm_liberty.py
maplibre/parse_root.py
maplibre/sources.py
maplibre/sprite.py
maplibre/style.json
maplibre/style_out.json
maplibre/tests.py
maplibre/transition.py
djangostreetmap-0.2.8.dist-info/METADATA
djangostreetmap-0.2.8.dist-info/WHEEL
djangostreetmap-0.2.8.dist-info/RECORD
