Metadata-Version: 2.1
Name: djangostreetmap
Version: 0.2.8
Summary: Deliver OpenstreetMap data in GeoJSON and MVT tile formats
Home-page: https://github.com/joshbrooks/djangostreetmap
License: LGPL-3.0-or-later
Author: Joshua Brooks
Author-email: josh.vdbroek@gmail.com
Requires-Python: >=3.8,<4.0
Classifier: License :: OSI Approved :: GNU Lesser General Public License v3 or later (LGPLv3+)
Classifier: Programming Language :: Python :: 3
Classifier: Programming Language :: Python :: 3.8
Classifier: Programming Language :: Python :: 3.9
Classifier: Programming Language :: Python :: 3.10
Classifier: Programming Language :: Python :: 3.11
Requires-Dist: osmflex (>=0.2.0,<0.3.0)
Requires-Dist: pydantic (>=1.10.0,<2.0.0)
Requires-Dist: typer (>=0.4.1,<0.5.0)
